<?xml version="1.0" encoding="UTF-8" standalone="yes"?>
<games>
    <game>
        <adverts>
            <advert>http://www.lemonamiga.com/games/adverts/full/3d_world_soccer_01.jpg</advert>
        </adverts>
        <boxes/>
        <coder>Mario Bruscella, Mario Savoia</coder>
        <design></design>
        <developer></developer>
        <disks>2</disks>
        <genre>Sports - Football/Soccer</genre>
        <graphics>Riccardo Cangini</graphics>
        <hardware>OCS, ECS</hardware>
        <language>English, German, French, Italian</language>
        <license>Commercial</license>
        <manager></manager>
        <musician></musician>
        <name>3D World Soccer</name>
        <players></players>
        <producer>Francesco Carla'</producer>
        <relationship></relationship>
        <reviews/>
        <shots>
            <shot>http://www.lemonamiga.com/games/screenshots/full/3d_world_soccer_01.png</shot>
            <shot>http://www.lemonamiga.com/games/screenshots/full/3d_world_soccer_02.png</shot>
            <shot>http://www.lemonamiga.com/games/screenshots/full/3d_world_soccer_03.png</shot>
            <shot>http://www.lemonamiga.com/games/screenshots/full/3d_world_soccer_04.png</shot>
            <shot>http://www.lemonamiga.com/games/screenshots/full/3d_world_soccer_05.png</shot>
            <shot>http://www.lemonamiga.com/games/screenshots/full/3d_world_soccer_06.png</shot>
            <shot>http://www.lemonamiga.com/games/screenshots/full/3d_world_soccer_07.png</shot>
            <shot>http://www.lemonamiga.com/games/screenshots/full/3d_world_soccer_08.png</shot>
            <shot>http://www.lemonamiga.com/games/screenshots/full/3d_world_soccer_09.png</shot>
        </shots>
        <url>http://www.lemonamiga.com/games/details.php?id=1496</url>
    </game>
</games>
