<?xml version="1.0" encoding="UTF-8" standalone="yes"?>
<games>
    <game>
        <adverts>
            <advert>http://www.lemonamiga.com/games/adverts/full/european_football_champ_01.jpg</advert>
        </adverts>
        <boxes/>
        <coder>Jon Broggy</coder>
        <design></design>
        <developer>Teque Software</developer>
        <disks>1</disks>
        <genre>Sports - Football/Soccer</genre>
        <graphics>Tony Hager</graphics>
        <hardware>OCS, ECS</hardware>
        <language>English</language>
        <license>Commercial</license>
        <manager></manager>
        <musician>Matt Furniss</musician>
        <name>European Football Champ</name>
        <players>1 or 2, Simultaneous</players>
        <producer></producer>
        <relationship></relationship>
        <reviews>
            <review>
                <link>http://amr.abime.net/review_40860</link>
                <magazine>Amiga Action 34 (Jul 1992)</magazine>
            </review>
            <review>
                <link>http://amr.abime.net/review_2733</link>
                <magazine>Amiga Format 62 (Aug 1994)</magazine>
            </review>
            <review>
                <link>http://amr.abime.net/review_22</link>
                <magazine>Amiga Power 15 (Jul 1992)</magazine>
            </review>
            <review>
                <link>http://amr.abime.net/review_1132</link>
                <magazine>Amiga Power 41 (Sep 1994)</magazine>
            </review>
            <review>
                <link>http://amr.abime.net/review_3463</link>
                <magazine>CU Amiga (Jul 1992)</magazine>
            </review>
            <review>
                <link>http://amr.abime.net/review_3906</link>
                <magazine>CU Amiga (Sep 1994)</magazine>
            </review>
            <review>
                <link>http://amr.abime.net/review_28524</link>
                <magazine>The One Amiga 46 (Jul 1992)</magazine>
            </review>
            <review>
                <link>http://amr.abime.net/review_9435</link>
                <magazine>The One Amiga 71 (Aug 1994)</magazine>
            </review>
        </reviews>
        <shots>
            <shot>http://www.lemonamiga.com/games/screenshots/full/european_football_champ_01.png</shot>
            <shot>http://www.lemonamiga.com/games/screenshots/full/european_football_champ_02.png</shot>
            <shot>http://www.lemonamiga.com/games/screenshots/full/european_football_champ_03.png</shot>
            <shot>http://www.lemonamiga.com/games/screenshots/full/european_football_champ_04.png</shot>
            <shot>http://www.lemonamiga.com/games/screenshots/full/european_football_champ_05.png</shot>
            <shot>http://www.lemonamiga.com/games/screenshots/full/european_football_champ_06.png</shot>
            <shot>http://www.lemonamiga.com/games/screenshots/full/european_football_champ_07.png</shot>
            <shot>http://www.lemonamiga.com/games/screenshots/full/european_football_champ_08.png</shot>
            <shot>http://www.lemonamiga.com/games/screenshots/full/european_football_champ_09.png</shot>
            <shot>http://www.lemonamiga.com/games/screenshots/full/european_football_champ_10.png</shot>
            <shot>http://www.lemonamiga.com/games/screenshots/full/european_football_champ_11.png</shot>
            <shot>http://www.lemonamiga.com/games/screenshots/full/european_football_champ_12.png</shot>
        </shots>
        <url>http://www.lemonamiga.com/games/details.php?id=2078</url>
    </game>
</games>
