<?xml version="1.0" encoding="UTF-8" standalone="yes"?>
<games>
    <game>
        <adverts>
            <advert>http://www.lemonamiga.com/games/adverts/full/mau-mau_01.jpg</advert>
        </adverts>
        <boxes/>
        <coder>Harald M&amp;uuml;ller</coder>
        <design></design>
        <developer></developer>
        <disks>1</disks>
        <genre>Cards - Miscellaneous</genre>
        <graphics></graphics>
        <hardware>OCS, ECS</hardware>
        <language>English</language>
        <license>Commercial</license>
        <manager></manager>
        <musician></musician>
        <name>Mau-Mau</name>
        <players></players>
        <producer></producer>
        <relationship></relationship>
        <reviews/>
        <shots>
            <shot>http://www.lemonamiga.com/games/screenshots/full/mau-mau_01.png</shot>
            <shot>http://www.lemonamiga.com/games/screenshots/full/mau-mau_02.png</shot>
        </shots>
        <url>http://www.lemonamiga.com/games/details.php?id=2970</url>
    </game>
</games>
