{
  "url": "https://www.generation-msx.nl/software/kaeru-soft/rockn-roller/3880/",
  "originalTitle": "Rock\u0027n Roller",
  "translatedTitle": "",
  "developedBy": "Kaeru Soft",
  "year": "1988",
  "system": "MSX",
  "sound": "PSG",
  "kind": "Game",
  "inputDevicesSupported": "Keyboard, Joystick",
  "genre": "ActionDexterity",
  "maxPlayers": "4",
  "maxSimultaneous": "4",
  "usesKanji": "",
  "license": "",
  "licence": "Commercial",
  "language": "Japanese",
  "note": "",
  "tagooDatabaseEntry": "",
  "credits": "",
  "mentions": [],
  "conversions": [],
  "releases": [
    {
      "title": "",
      "productCode": "",
      "pirated": "",
      "publisher": "Popcom Soft",
      "country": "Japan ",
      "media": "Double Side Disk "
    },
    {
      "title": "",
      "productCode": "",
      "pirated": "",
      "publisher": "MSX Resource Center",
      "country": "",
      "media": "ROM (16kB)"
    },
    {
      "title": "",
      "productCode": "",
      "pirated": "",
      "publisher": "",
      "country": "",
      "media": " "
    }
  ],
  "medias": [
    {
      "url": "//images.generation-msx.nl/cover/09eb9589.png",
      "type": "image",
      "title": "Front"
    },
    {
      "url": "//images.generation-msx.nl/cover/db37ce74.jpg",
      "type": "image",
      "title": "Manual"
    },
    {
      "url": "//images.generation-msx.nl/cover/d69569f0.jpg",
      "type": "image",
      "title": "Manual"
    },
    {
      "url": "",
      "type": "image",
      "title": ""
    },
    {
      "url": "//images.generation-msx.nl/software_title/b1a6bd5b.png",
      "type": "image",
      "title": "Title screen."
    },
    {
      "url": "//images.generation-msx.nl/software_game/774dc29c.png",
      "type": "image",
      "title": "Game screen."
    },
    {
      "url": "//images.generation-msx.nl/software_extra/e631a738.png",
      "type": "image",
      "title": ""
    },
    {
      "url": "//images.generation-msx.nl/software_extra/30dcbbaf.png",
      "type": "image",
      "title": ""
    },
    {
      "url": "//images.generation-msx.nl/software_extra/4fafe591.png",
      "type": "image",
      "title": ""
    },
    {
      "url": "//images.generation-msx.nl/software_extra/85cd04fc.png",
      "type": "image",
      "title": ""
    },
    {
      "url": "",
      "type": "image",
      "title": ""
    }
  ]
}