{
  "name": "Arcus",
  "url": "http://www.msxgamesworld.com/gamecard.php?id=1567",
  "MGW ID": "1567",
  "Type": "Game",
  "License": "Commercial",
  "Developed by": "Wolf Team",
  "Released by": "Wolf Team",
  "Year of release": "1988",
  "Generation": "MSX2",
  "Genre": "RPG",
  "Format": [
    "Disk",
    "(2DD)",
    "x3"
  ],
  "Sound": [
    "PSG",
    "MSX-MUSIC"
  ],
  "Number of players": "1",
  "Languages": "Japanese",
  "Controls": [
    "Keyboard",
    "Joystick"
  ],
  "Requires": "128Kb VRAM",
  "Price": "8800 JPY - Japan Yen",
  "Region": "Asia",
  "Country": "Japan",
  "caratulas": [
    "images/caratulas/Arcus (Wolf Team, 1988) 001.jpg"
  ],
  "capturas": [
    "images/capturas/Arcus (Wolf Team, 1988) 001.png",
    "images/capturas/Arcus (Wolf Team, 1988) 002.png",
    "images/capturas/Arcus (Wolf Team, 1988) 003.png",
    "images/capturas/Arcus (Wolf Team, 1988) 004.png"
  ]
}