<?xml version="1.0" encoding="UTF-8" standalone="yes"?>
<games>
    <game>
        <capturas>
            <captura>images/capturas/mission2mir(1).png</captura>
            <captura>images/capturas/mission2mir(2).png</captura>
            <captura>images/capturas/mission2mir(3).png</captura>
            <captura>images/capturas/mission2mir(4).png</captura>
            <captura>images/capturas/mission2mir(5).png</captura>
            <captura>images/capturas/mission2mir(6).png</captura>
            <captura>images/capturas/mission2mir(7).png</captura>
            <captura>images/capturas/mission2mir(1).png</captura>
            <captura>images/capturas/mission2mir(2).png</captura>
            <captura>images/capturas/mission2mir(3).png</captura>
            <captura>images/capturas/mission2mir(4).png</captura>
            <captura>images/capturas/knuckle_joe(4).png</captura>
        </capturas>
        <caratulas/>
        <control>Keyboard Joystick</control>
        <country></country>
        <developer>RAY2DAY MSX SOFTWARE</developer>
        <format>ROM cartridge</format>
        <generation>MSX</generation>
        <languages>English</languages>
        <name>Mission2Mir</name>
        <players>1</players>
        <price></price>
        <productId></productId>
        <publisher></publisher>
        <region></region>
        <releases/>
        <remakes/>
        <requires></requires>
        <sound>PSG</sound>
        <type>Shoot'em up</type>
        <typeOfLicense></typeOfLicense>
        <url>http://msxgamesworld.com/gamecard.php?id=2932</url>
        <year>2010</year>
    </game>
</games>
