<?xml version="1.0" encoding="UTF-8" standalone="yes"?>
<games>
    <game>
        <capturas>
            <captura>images/capturas2/Combate (Unknown, 1986) (1).png</captura>
            <captura>images/capturas2/Combate (Unknown, 1986) (2).png</captura>
            <captura>images/capturas2/Combate (Unknown, 1986) (3).png</captura>
            <captura>images/capturas2/Combate (Unknown, 1986) (4).png</captura>
            <captura>images/capturas/Cobras Arc (Dinamic, 1986) (6).png</captura>
        </capturas>
        <caratulas/>
        <control>Joystick</control>
        <country>Brazil</country>
        <developer>Unknown</developer>
        <format>ROM cartridge</format>
        <generation>MSX</generation>
        <languages>Portuguese</languages>
        <name>Combate</name>
        <players>1</players>
        <price></price>
        <productId></productId>
        <publisher>Unknown</publisher>
        <region>America</region>
        <releases/>
        <remakes/>
        <requires></requires>
        <sound>PSG</sound>
        <type>Arcade</type>
        <typeOfLicense></typeOfLicense>
        <url>http://msxgamesworld.com/gamecard.php?id=4592</url>
        <year>1986</year>
    </game>
</games>
