{"altername_name": [], "name": "Myth Makers: Trixie in Toyland", "overview": "Join the Myth Makers in their latest adventure... Trixie in Toyland! The evil Penumbra, leader of the Acrostic Riders has stolen the Myth Makers Orbs and has hidden it from Toyland. Trixie must explore every inch of Toyland and find the stolen orbs and return balance to the Myth realm. But its not going to be easy! Along her way, Trixie must do battle with killer clows, rampaging robots, and hovering helecopters! Features \u2022 Pounce on enemies from above and then follow up with the magic rattle and knock them into next week! \u2022 Collect power ups to increase the power and accuracy of Trixie's weapons. \u2022 Hop, skip and jump your way around the many Toyland levels and find the missing Magical Orbs!", "platform": "Nintendo Wii", "release_date": "June 24, 2008", "game_type": "Released", "esrb": "", "developers": "", "publishers": "", "genres": "", "max_players": "", "cooperative": "No", "rating": "1.25", "wikipedia": "https://en.wikipedia.org/wiki/Myth_Makers:_Trixie_in_Toyland", "video_link": "", "launchbox_gamesdb_link": "https://gamesdb.launchbox-app.com/games/details/13434-myth-makers-trixie-in-toyland\n"}