<?xml version="1.0" encoding="UTF-8" standalone="yes"?>
<computers>
    <computer>
        <adverts/>
        <builtInGames>GRID BASIC</builtInGames>
        <colors>Monochrome</colors>
        <controllers></controllers>
        <coprocessor>8087 math coprocessor</coprocessor>
        <cpu>Intel 8086</cpu>
        <description>
The Compass portable was the first computer of the Grid company; and the very first clamshell laptop (GRiD had the patent on the clamshell idea).

It was an expensive portable business computer incorporating large memories (both RAM and data storage) for the time, but above all one of the first graphic amber plasma flat screen.

It was housed in in a matt-black finished magnesium case. Not only does this gave increased protection (and weight) that some plastic shells, it also acted as a heat-sink, so there was no cooling fan. Stangely, there was no carrying handle either. Above the keyboard was a panel displaying common command codes to refresh user's memory.

Instead of a disk drive, first Compass held a 384 KB non-volatile bubble memory (like the Sharp PC-5000). Software could be loaded from a Grid server, however, user could connect an external 360 KB floppy disc or 10 MB hard disk unit. The Compass also featured a built-in modem.
_______________________</description>
        <emulators/>
        <graphics>320 x 240 dots</graphics>
        <hardwares/>
        <image>http://www.old-computers.com/museum/photos/grid_compass_2s.jpg</image>
        <keyboard>Full stroke 57 keys</keyboard>
        <language>GRID BASIC</language>
        <links/>
        <manufacturer>Grid</manufacturer>
        <media>384 KB bubble RAM</media>
        <name>Compass</name>
        <numGames></numGames>
        <origin>U.S.A.</origin>
        <peripherals>RAM cards, 360 KB 5.25'' floppy disc unit, 10 MB hard disk unit</peripherals>
        <ports>Serial RS-232, RS-422, IEEE-488</ports>
        <power>Built-in poxer supply unit</power>
        <price>&amp;pound;4595 (U.K., 1984)</price>
        <production></production>
        <ram>256 KB (up to 512 KB)</ram>
        <rom>Unknown</rom>
        <screenshots>
            <shot>
                <description>&amp;lt;br&amp;gt;&amp;lt;font color=&amp;quot;red&amp;quot;&amp;gt;&amp;lt;strong&amp;gt;&amp;amp;gt;&amp;amp;nbsp;GRID COMPASS&amp;lt;/strong&amp;gt;&amp;lt;/font&amp;gt;&amp;lt;br&amp;gt;&amp;lt;blockquote&amp;gt;&amp;lt;</description>
                <link>http://www.old-computers.com/museum/photos/grid_compass_2.jpg</link>
            </shot>
            <shot>
                <description>&amp;lt;br&amp;gt;&amp;lt;font color=&amp;quot;red&amp;quot;&amp;gt;&amp;lt;strong&amp;gt;&amp;amp;gt;&amp;amp;nbsp;ANOTHER VIEW&amp;lt;/strong&amp;gt;&amp;lt;/font&amp;gt;&amp;lt;br&amp;gt;&amp;lt;blockquote&amp;gt;&amp;lt;</description>
                <link>http://www.old-computers.com/museum/photos/grid_compass_redrum76_1.jpg</link>
            </shot>
            <shot>
                <description>&amp;lt;br&amp;gt;&amp;lt;font color=&amp;quot;red&amp;quot;&amp;gt;&amp;lt;strong&amp;gt;&amp;amp;gt;&amp;amp;nbsp;B&amp;amp;W PICTURE&amp;lt;/strong&amp;gt;&amp;lt;/font&amp;gt;&amp;lt;br&amp;gt;&amp;lt;blockquote&amp;gt;&amp;lt;</description>
                <link>http://www.old-computers.com/museum/photos/Grid_Compass_System_1.jpg</link>
            </shot>
            <shot>
                <description>&amp;lt;br&amp;gt;&amp;lt;font color=&amp;quot;red&amp;quot;&amp;gt;&amp;lt;strong&amp;gt;&amp;amp;gt;&amp;amp;nbsp;CLOSED&amp;lt;/strong&amp;gt;&amp;lt;/font&amp;gt;&amp;lt;br&amp;gt;&amp;lt;blockquote&amp;gt;&amp;lt;</description>
                <link>http://www.old-computers.com/museum/photos/grid_compass_closed.jpg</link>
            </shot>
            <shot>
                <description>&amp;lt;br&amp;gt;&amp;lt;font color=&amp;quot;red&amp;quot;&amp;gt;&amp;lt;strong&amp;gt;&amp;amp;gt;&amp;amp;nbsp;INSIDE&amp;lt;/strong&amp;gt;&amp;lt;/font&amp;gt;&amp;lt;br&amp;gt;&amp;lt;blockquote&amp;gt;&amp;lt;</description>
                <link>http://www.old-computers.com/museum/photos/grid_compass_inside.jpg</link>
            </shot>
            <shot>
                <description>&amp;lt;br&amp;gt;&amp;lt;font color=&amp;quot;red&amp;quot;&amp;gt;&amp;lt;strong&amp;gt;&amp;amp;gt;&amp;amp;nbsp;DISPLAY OPENED&amp;lt;/strong&amp;gt;&amp;lt;/font&amp;gt;&amp;lt;br&amp;gt;&amp;lt;blockquote&amp;gt;&amp;lt;</description>
                <link>http://www.old-computers.com/museum/photos/grid_compass_monitor.jpg</link>
            </shot>
            <shot>
                <description>&amp;lt;br&amp;gt;&amp;lt;font color=&amp;quot;red&amp;quot;&amp;gt;&amp;lt;strong&amp;gt;&amp;amp;gt;&amp;amp;nbsp;COMPASS BAG&amp;lt;/strong&amp;gt;&amp;lt;/font&amp;gt;&amp;lt;br&amp;gt;&amp;lt;blockquote&amp;gt;&amp;lt;</description>
                <link>http://www.old-computers.com/museum/photos/Grid_Compass_Bag_1.jpg</link>
            </shot>
        </screenshots>
        <size>38 (H) x 29 (D) x 5 (H) cm / 8.5 lbs (4.3 kg)</size>
        <sound>Beeper</sound>
        <speed>Unknown</speed>
        <text>80 chars x 25 lines</text>
        <type>Portable</type>
        <vram>Unknown</vram>
        <year>April 1982</year>
    </computer>
</computers>
