{
  "name": "Pocket Billiards: Funk the 9 Ball",
  "shortName": "pocket-billiards-funk-the-9-ball",
  "description": "A billiards game where you collect spirits called Tamapi to store inside balls to affect gameplay when sunk into a pocket, such as shaking the table or getting another turn if you fail to pocket a ball on a turn. Collect more spirits from opponents by defeating them. During the rounds of billiards you can win items such as MiniDiscs to unlock new music for the DJ to play in the background.",
  "publishedBy": "Tamsoft Corporation",
  "developedBy": "SunTech Company Limited",
  "released": "Feb 19, 2000",
  "alsoFor": "",
  "genre": "Sports",
  "perspective": "Top-down",
  "theme": "",
  "nonSport": "",
  "sport": "Pool / snooker",
  "misc": "",
  "country": "",
  "releaseDate": "",
  "url": "https://www.mobygames.com/game/gameboy-color/pocket-billiards-funk-the-9-ball",
  "visual": "Fixed / flip-screen",
  "gamePlay": "",
  "setting": "",
  "release": [
    {
      "system": "Game Boy Color",
      "releases": [
        {
          "publisher": "Tamsoft Corporation",
          "developer": "SunTech Company Limited",
          "ported": "",
          "country": " Japan",
          "releaseDate": "Feb 19, 2000",
          "ean13": "",
          "comments": ""
        }
      ]
    }
  ],
  "shot": [],
  "cover": []
}