{"altername_name": [], "name": "Takahashi Shoten Kanshuu: Saihinshutsu! SPI Perfect Mondaishuu DS: 2011 Nendo Ban", "overview": "Takahashi Shoten Kanshuu: Saihinshutsu! SPI Perfect Mondaishuu DS 2011 Nendohan is a Miscellaneous game, developed and published by Genki, which was released in Japan in 2010.", "platform": "Nintendo DS", "release_date": "January 14, 2010", "game_type": "Released", "esrb": "", "developers": "Genki", "publishers": "Genki", "genres": "Education", "max_players": "1", "cooperative": "No", "rating": "None", "wikipedia": "", "video_link": "", "launchbox_gamesdb_link": "https://gamesdb.launchbox-app.com/games/details/135204-takahashi-shoten-kanshuu-saihinshutsu-spi-perfect-mondaishuu-ds-2011-nendo-ban\n"}