{"altername_name": [], "name": "Arcade Classics", "overview": "Compilation including unofficial clones of four classic arcade games (three of which are shooters): - Asteroids (called Rocks in Space on the in-game title screen) - Snakes (called Worm Warz on the in-game title screen) - Space Invaders (called Invaders on the in-game title screen) - Space Wars", "platform": "Commodore 64", "release_date": "1987", "game_type": "Released", "esrb": "Not Rated", "developers": "Dave Korn (Ubik)", "publishers": "Firebird Software", "genres": "Action", "max_players": "2", "cooperative": "No", "rating": "4.43", "wikipedia": "", "video_link": "https://www.youtube.com/watch?v=lopYfa0knuo", "launchbox_gamesdb_link": "https://gamesdb.launchbox-app.com/games/details/87270-arcade-classics\n"}