{"altername_name": [], "name": "Cave Climber", "overview": "This tough little platformer is a German language clone of the 1983 Konami arcade game Roc 'N Rope. It was developed by Thorsten Lange and published by Verlag Heinz Heise GmbH in Input 64 1985/09. An English translation under the name Rock 'N Rope name was completed but never officially published.", "platform": "Commodore 64", "release_date": "1985", "game_type": "Released", "esrb": "Not Rated", "developers": "Thorsten Lange", "publishers": "Verlag Heinz Heise", "genres": "Platform", "max_players": "1", "cooperative": "No", "rating": "None", "wikipedia": "", "video_link": "https://www.youtube.com/watch?v=E9HfT38Hwyg", "launchbox_gamesdb_link": "https://gamesdb.launchbox-app.com/games/details/90382-cave-climber\n"}