{"altername_name": [], "name": "Pillars", "overview": "Pillars is a 1-2 player competitive Columns inspired puzzle game for the Commodore 64. It was developed by Arlasoft and released on his itch.io page on December 18, 2021.", "platform": "Commodore 64", "release_date": "December 18, 2021", "game_type": "Homebrew", "esrb": "Not Rated", "developers": "Arlasoft", "publishers": "", "genres": "Puzzle", "max_players": "2", "cooperative": "No", "rating": "4", "wikipedia": "", "video_link": "", "launchbox_gamesdb_link": "https://gamesdb.launchbox-app.com/games/details/157449-pillars\n"}