{"altername_name": [], "name": "Sokoban 64", "overview": "Sokoban is a puzzle video game in which the player pushes crates or boxes around in a warehouse, trying to get them to storage locations.", "platform": "Commodore 64", "release_date": "2014", "game_type": "Homebrew", "esrb": "Not Rated", "developers": "Steve Ody", "publishers": "Uppercase Software", "genres": "Puzzle", "max_players": "1", "cooperative": "No", "rating": "None", "wikipedia": "", "video_link": "", "launchbox_gamesdb_link": "https://gamesdb.launchbox-app.com/games/details/127846-sokoban-64\n"}