{"altername_name": ["Sangoku Musou"], "name": "Dynasty Warriors", "overview": "Based on the historical novel, \"Romance of the Three Kingdoms, \" Dynasty Warriors puts you right in the center of the upheaval of 3rd century China, when legendary warlords fought to expand and unite realms under their own banners. Enter a time of struggle, when warriors were as cunning as they were courageous. Master the dynamic game play. Wisely balance elaborate offensive strikes, with precisely timed defensive maneuvers and flurries of whirling counter attacks. Then, train to unleash the killer combination in martial mastery to become the Musou - the Warrior Unequaled!", "platform": "Sony Playstation", "release_date": "February 28, 1997", "game_type": "Released", "esrb": "T - Teen", "developers": "Omega Force", "publishers": "Koei", "genres": "Beat 'em Up", "max_players": "2", "cooperative": "No", "rating": "3.53", "wikipedia": "https://en.wikipedia.org/wiki/Dynasty_Warriors_(video_game)", "video_link": "", "launchbox_gamesdb_link": "https://gamesdb.launchbox-app.com/games/details/13745-dynasty-warriors\n"}