<?xml version="1.0" encoding="UTF-8" standalone="yes"?>
<computer>
    <adverts>
        <advert>
            <description>&amp;lt;br&amp;gt;&amp;lt;font color=&amp;quot;red&amp;quot;&amp;gt;&amp;lt;strong&amp;gt;&amp;gt;&amp;nbsp;US AD. JUNE 1983&amp;lt;/strong&amp;gt;&amp;lt;/font&amp;gt;&amp;lt;br&amp;gt;&amp;lt;blockquote&amp;gt;This advert puts forward network capabilities of Televideo systems.&amp;lt;br&amp;gt;&amp;lt;br&amp;gt;&amp;lt;font color=&amp;quot;#666666&amp;quot;&amp;gt; ... If you want a personal computer that gives you professional performances, it's obvious that you have a lot of choices for today.&amp;lt;br&amp;gt; But there's only one with choices for tomorrow. Televideo ...&amp;lt;/font&amp;gt; &amp;lt;/blockquote&amp;gt;</description>
            <link>http://www.old-computers.com/museum/adverts/Televideo_PM4T_Advert_1.jpg</link>
        </advert>
        <advert>
            <description>&amp;lt;br&amp;gt;&amp;lt;font color=&amp;quot;red&amp;quot;&amp;gt;&amp;lt;strong&amp;gt;&amp;gt;&amp;nbsp;US AD. AUGUST 1985&amp;lt;/strong&amp;gt;&amp;lt;/font&amp;gt;&amp;lt;br&amp;gt;&amp;lt;blockquote&amp;gt;&amp;lt;/blockquote&amp;gt;</description>
            <link>http://www.old-computers.com/museum/adverts/Televideo_PM4T_Advert_s2.jpg</link>
        </advert>
    </adverts>
    <batteries></batteries>
    <builtInGames>5.25'' disk-drive</builtInGames>
    <buttons></buttons>
    <colors>Unknown</colors>
    <controllers></controllers>
    <coprocessor>N/A</coprocessor>
    <cpu>Zilog Z80A + Intel 80186</cpu>
    <description>
The Mini PM/4T was the multi-user version of the Televideo PC compatible. A video terminal was used for interfacing directly to the system.

The InfoShare Operating System can run many multi-user programs or execute most single-user MS-DOS programs.

The PM/4T can be linked to up to four computers (PCs or Televideo's PM Workstation [a terminal]).

It was sold for $6000, and a 16-user version was available at $9000.
A $99 card was required to connect each PC to the system.

Igor Pronin reports :
I was one of the first users in Finland. Infoshare Operating System was actually Novell Netware. In the begining it was version 1 or 1.1 but it was soon upgraded to 1.2. As a server running programs off the server, it was faster than from a local hard disk of a 12 MHz AT.
 


</description>
    <emulators/>
    <graphics>Unknown</graphics>
    <gun></gun>
    <hardwares/>
    <image>http://www.old-computers.com/museum/photos/televideo_mini-pm4t_1.jpg</image>
    <keyboard>Unknown</keyboard>
    <language></language>
    <links/>
    <manufacturer>Televideo</manufacturer>
    <media>5.25'' disk-drive</media>
    <name>Personal Mini PM/4T</name>
    <numGames></numGames>
    <origin>U.S.A.</origin>
    <peripherals></peripherals>
    <ports>RS 232C (Two) - RS 422 (Serial port - Four) - Centronics</ports>
    <power>Built-in PSU</power>
    <price>$6000</price>
    <production></production>
    <ram>1024 KB (some systems may have more or less memory)</ram>
    <rom>Unknown</rom>
    <screenshots/>
    <size>Unknown</size>
    <sound>Unknown</sound>
    <speed></speed>
    <switches></switches>
    <text>Unknown</text>
    <type>Professional Computer</type>
    <vram>N/A</vram>
    <year>1984</year>
</computer>
