{"altername_name": [], "name": "4 Most Super Sports", "overview": "4 Most Super Sports is a compilation of the following four games: - US Basket Master - Kentucky Racing - Championship Sprint - Howzat", "platform": "Sinclair ZX Spectrum", "release_date": "1992", "game_type": "Released", "esrb": "Not Rated", "developers": "", "publishers": "Alternative Software", "genres": "Sports", "max_players": "", "cooperative": "No", "rating": "4.62", "wikipedia": "", "video_link": "", "launchbox_gamesdb_link": "https://gamesdb.launchbox-app.com/games/details/148840-4-most-super-sports\n"}