{"altername_name": [], "name": "E.X. Troopers", "overview": "An offshoot of the Lost Planet franchise, EX Troopers is an action game focused as much on character dynamics in a pilot school as it is on alien-blasting action.", "platform": "Nintendo 3DS", "release_date": "November 22, 2012", "game_type": "Released", "esrb": "", "developers": "", "publishers": "Capcom", "genres": "", "max_players": "", "cooperative": "No", "rating": "4.31", "wikipedia": "", "video_link": "", "launchbox_gamesdb_link": "https://gamesdb.launchbox-app.com/games/details/14996-ex-troopers\n"}