{
  "name": "Custom Robo V2",
  "shortName": "custom-robo-v2",
  "description": "<i>Custom Robo V2</i> is the second game in the <i>Custom Robo</i> series. It is similar to the first, but it features tag teaming. The player travels an overworld, and participates in Custom Robo battles. The goal of the game is to win every battle of the storyline while collecting every Robo, battle part, and item.",
  "publishedBy": "Nintendo Co., Ltd.",
  "developedBy": "Noise, Inc.",
  "released": "Nov 10, 2000",
  "alsoFor": "Wii, Wii U | Combined View",
  "genre": "Action, Role-Playing (RPG)",
  "perspective": "Bird's-eye view",
  "theme": "",
  "nonSport": "",
  "sport": "",
  "misc": "",
  "country": "",
  "releaseDate": "",
  "url": "https://www.mobygames.com/game/n64/custom-robo-v2",
  "visual": "",
  "gamePlay": "Fighting",
  "setting": "",
  "release": [
    {
      "system": "Nintendo 64",
      "releases": [
        {
          "publisher": "Nintendo Co., Ltd.",
          "developer": "Noise, Inc.",
          "ported": "",
          "country": " Japan",
          "releaseDate": "Nov 10, 2000",
          "ean13": "4 902370 504996",
          "comments": ""
        }
      ]
    }
  ],
  "shot": [],
  "cover": [
    {
      "link": "/images/covers/l/704905-custom-robo-v2-nintendo-64-front-cover.jpg",
      "scanOf": "Front Cover",
      "packaging": "Box",
      "country": "Japan",
      "platforms": "Nintendo 64"
    },
    {
      "link": "/images/covers/l/704906-custom-robo-v2-nintendo-64-front-cover.jpg",
      "scanOf": "Front Cover",
      "packaging": "Box",
      "country": "Japan",
      "platforms": "Nintendo 64"
    },
    {
      "link": "/images/covers/l/704912-custom-robo-v2-nintendo-64-spine-sides.jpg",
      "scanOf": "Spine/Sides",
      "packaging": "Box",
      "country": "Japan",
      "platforms": "Nintendo 64"
    },
    {
      "link": "/images/covers/l/704913-custom-robo-v2-nintendo-64-spine-sides.jpg",
      "scanOf": "Spine/Sides",
      "packaging": "Box",
      "country": "Japan",
      "platforms": "Nintendo 64"
    },
    {
      "link": "/images/covers/l/704910-custom-robo-v2-nintendo-64-media.jpg",
      "scanOf": "Media",
      "packaging": "Box",
      "country": "Japan",
      "platforms": "Nintendo 64"
    },
    {
      "link": "/images/covers/l/704907-custom-robo-v2-nintendo-64-manual.jpg",
      "scanOf": "Manual",
      "packaging": "Box",
      "country": "Japan",
      "platforms": "Nintendo 64"
    },
    {
      "link": "/images/covers/l/704908-custom-robo-v2-nintendo-64-manual.jpg",
      "scanOf": "Manual",
      "packaging": "Box",
      "country": "Japan",
      "platforms": "Nintendo 64"
    }
  ]
}