{"name": "Kidou Senshi Gundam Vol. 2: Jaburo", "overview": "The second in a trilogy of Wonderswan games that are based on the original Mobile Suit Gundam anime. This game covers episodes 13-30 of the show.", "platform": "WonderSwan Color", "release_date": "August 16, 2001", "game_type": "Released", "esrb": "Not Rated", "developers": "Bandai", "publishers": "Bandai", "genres": "Strategy", "max_players": "1", "cooperative": "No", "rating": "3", "wikipedia": "", "video_link": "", "launchbox_gamesdb_link": "https://gamesdb.launchbox-app.com/games/details/27948\n"}