{"altername_name": [], "name": "Strawberry Daisenryaku II", "overview": "A relatively simple strategy conquest game, set in a land where you are apparently the only male. Besides the usual army construction and management, you also can have sex with your various female cohorts.", "platform": "NEC PC-9801", "release_date": "1993", "game_type": "Released", "esrb": "", "developers": "FairyTale", "publishers": "FairyTale", "genres": "Strategy", "max_players": "1", "cooperative": "No", "rating": "None", "wikipedia": "", "video_link": "", "launchbox_gamesdb_link": "https://gamesdb.launchbox-app.com/games/details/141557-strawberry-daisenryaku-ii\n"}