<?xml version="1.0" encoding="UTF-8" standalone="yes"?>
<computer>
    <adverts>
        <advert>
            <description>&amp;lt;br&amp;gt;&amp;lt;font color=&amp;quot;red&amp;quot;&amp;gt;&amp;lt;strong&amp;gt;&amp;gt;&amp;nbsp;US ADVERT #1&amp;lt;/strong&amp;gt;&amp;lt;/font&amp;gt;&amp;lt;br&amp;gt;&amp;lt;blockquote&amp;gt;&amp;lt;p class=&amp;quot;petitgris&amp;quot;&amp;gt;Picture courtesy of &amp;lt;a href=&amp;quot;http://www.sbrowning.com/vintage&amp;quot;&amp;gt;Steve Browning, www.sbrowning.com/vintage&amp;lt;/a&amp;gt;.&amp;lt;/p&amp;gt;&amp;lt;/blockquote&amp;gt;</description>
            <link>http://www.old-computers.com/museum/adverts/tandy_trs80-coco1_ad_1.jpg</link>
        </advert>
        <advert>
            <description>&amp;lt;br&amp;gt;&amp;lt;font color=&amp;quot;red&amp;quot;&amp;gt;&amp;lt;strong&amp;gt;&amp;gt;&amp;nbsp;JAPANESE ADVERT #3&amp;lt;/strong&amp;gt;&amp;lt;/font&amp;gt;&amp;lt;br&amp;gt;&amp;lt;blockquote&amp;gt;&amp;lt;p class=&amp;quot;petitgris&amp;quot;&amp;gt;Thanks to &amp;lt;a href=&amp;quot;http://osaki.cool.ne.jp/hc/computer/canon/canon.html#x07&amp;quot;&amp;gt;Handheld computer &amp;amp; Pocket calculator Museum&amp;lt;/a&amp;gt; for this picture&amp;lt;/p&amp;gt;&amp;lt;/blockquote&amp;gt;</description>
            <link>http://www.old-computers.com/museum/adverts/canon_x07_jap-advert_2.jpg</link>
        </advert>
        <advert>
            <description>&amp;lt;br&amp;gt;&amp;lt;font color=&amp;quot;red&amp;quot;&amp;gt;&amp;lt;strong&amp;gt;&amp;gt;&amp;nbsp;CHARLIE CHAPLIN #2&amp;lt;/strong&amp;gt;&amp;lt;/font&amp;gt;&amp;lt;br&amp;gt;&amp;lt;blockquote&amp;gt;1982 - It was the time when one still lacked good programs for the IBM PC...&amp;lt;br&amp;gt;&amp;lt;br&amp;gt; Advert said: &amp;lt;font color=&amp;quot;#666666&amp;quot;&amp;gt;&amp;lt;br&amp;gt;&amp;lt;br&amp;gt; Attention, all programmers. Here's a chance to reach the top.&amp;lt;br&amp;gt; If you've written software that's completed and runs on the IBM Personal Computer (or another computer), we could be interested in publishing it...&amp;lt;br&amp;gt; ... We select programs that will make the IBM Personal Computer an even more useful toll for modern times...&amp;lt;/font&amp;gt;&amp;lt;/blockquote&amp;gt;</description>
            <link>http://www.old-computers.com/museum/adverts/IBM_5150_ChaplinAdvert_2.jpg</link>
        </advert>
        <advert>
            <description>&amp;lt;br&amp;gt;&amp;lt;font color=&amp;quot;red&amp;quot;&amp;gt;&amp;lt;strong&amp;gt;&amp;gt;&amp;nbsp;SIL'Z III&amp;lt;/strong&amp;gt;&amp;lt;/font&amp;gt;&amp;lt;br&amp;gt;&amp;lt;blockquote&amp;gt;Nice fish-eye picture of a Sil'z III illustrating a 1982 article about Technologic Revolution in the french mag TeleSoft.&amp;lt;/blockquote&amp;gt;</description>
            <link>http://www.old-computers.com/museum/adverts/leanord_silz3_pic_rev_1.jpg</link>
        </advert>
        <advert>
            <description>&amp;lt;br&amp;gt;&amp;lt;font color=&amp;quot;red&amp;quot;&amp;gt;&amp;lt;strong&amp;gt;&amp;gt;&amp;nbsp;FIRST ADVERT - FEB.1982&amp;lt;/strong&amp;gt;&amp;lt;/font&amp;gt;&amp;lt;br&amp;gt;&amp;lt;blockquote&amp;gt;&amp;lt;p class=&amp;quot;petitgris&amp;quot;&amp;gt;Courtesy of &amp;lt;b&amp;gt;&amp;lt;a href=&amp;quot;http://www.aci.com.pl/mwichary/&amp;quot; target=&amp;quot;_blank&amp;quot;&amp;gt;Attached&amp;lt;/a&amp;gt;&amp;lt;/b&amp;gt;&amp;lt;/p&amp;gt;&amp;lt;/blockquote&amp;gt;</description>
            <link>http://www.old-computers.com/museum/adverts/IBM_5150_Advert81_s3.jpg</link>
        </advert>
        <advert>
            <description>&amp;lt;br&amp;gt;&amp;lt;font color=&amp;quot;red&amp;quot;&amp;gt;&amp;lt;strong&amp;gt;&amp;gt;&amp;nbsp;ITALIAN AD&amp;lt;/strong&amp;gt;&amp;lt;/font&amp;gt;&amp;lt;br&amp;gt;&amp;lt;blockquote&amp;gt;&amp;ldquo;Why be content with a video game system?&amp;lt;br&amp;gt; Today, the VIC-20 is available at a special price.&amp;rdquo;&amp;lt;p class=&amp;quot;petitgris&amp;quot;&amp;gt;Courtesy of &amp;lt;b&amp;gt;http://angelmemories.cjb.net/&amp;lt;/b&amp;gt;&amp;lt;/p&amp;gt;&amp;lt;/blockquote&amp;gt;</description>
            <link>http://www.old-computers.com/museum/adverts/Commodore_Vic20_AdItaly_1.jpg</link>
        </advert>
        <advert>
            <description>&amp;lt;br&amp;gt;&amp;lt;font color=&amp;quot;red&amp;quot;&amp;gt;&amp;lt;strong&amp;gt;&amp;gt;&amp;nbsp;FRENCH ADVERT (SEPTEMBER 1984)&amp;lt;/strong&amp;gt;&amp;lt;/font&amp;gt;&amp;lt;br&amp;gt;&amp;lt;blockquote&amp;gt;&amp;lt;/blockquote&amp;gt;</description>
            <link>http://www.old-computers.com/museum/adverts/zenith_z100_advert_1.jpg</link>
        </advert>
        <advert>
            <description>&amp;lt;br&amp;gt;&amp;lt;font color=&amp;quot;red&amp;quot;&amp;gt;&amp;lt;strong&amp;gt;&amp;gt;&amp;nbsp;FRENCH AD (DEC. 1983)&amp;lt;/strong&amp;gt;&amp;lt;/font&amp;gt;&amp;lt;br&amp;gt;&amp;lt;blockquote&amp;gt;&amp;quot;Sorry, you don't play with me&amp;quot;&amp;lt;/blockquote&amp;gt;</description>
            <link>http://www.old-computers.com/museum/adverts/rair_business-computer_ad_1.jpg</link>
        </advert>
        <advert>
            <description>&amp;lt;br&amp;gt;&amp;lt;font color=&amp;quot;red&amp;quot;&amp;gt;&amp;lt;strong&amp;gt;&amp;gt;&amp;nbsp;PROMOTIONAL PICTURE&amp;lt;/strong&amp;gt;&amp;lt;/font&amp;gt;&amp;lt;br&amp;gt;&amp;lt;blockquote&amp;gt;&amp;lt;p class=&amp;quot;petitgris&amp;quot;&amp;gt;thanks to datareign.co.uk for this picture&amp;lt;/p&amp;gt;&amp;lt;/blockquote&amp;gt;</description>
            <link>http://www.old-computers.com/museum/adverts/pertec_pcc2000_ad_1.jpg</link>
        </advert>
        <advert>
            <description>&amp;lt;br&amp;gt;&amp;lt;font color=&amp;quot;red&amp;quot;&amp;gt;&amp;lt;strong&amp;gt;&amp;gt;&amp;nbsp;1ST. U.S. ADVERT #2&amp;lt;/strong&amp;gt;&amp;lt;/font&amp;gt;&amp;lt;br&amp;gt;&amp;lt;blockquote&amp;gt;Each picture represents a customers target. Three of them are well known: Home/entertainement,  office and educational uses. A fourth one is added for the first time, the senior citizens. Epson thought the QX-10 was user-friendly enough to be used by retired people.   &amp;lt;/blockquote&amp;gt;</description>
            <link>http://www.old-computers.com/museum/adverts/Epson_QX10_Advert_2.jpg</link>
        </advert>
        <advert>
            <description>&amp;lt;br&amp;gt;&amp;lt;font color=&amp;quot;red&amp;quot;&amp;gt;&amp;lt;strong&amp;gt;&amp;gt;&amp;nbsp;MBC-550 FRENCH ADVERT&amp;lt;/strong&amp;gt;&amp;lt;/font&amp;gt;&amp;lt;br&amp;gt;&amp;lt;blockquote&amp;gt;''The personal computer 550, an opened door upon you computing future''&amp;lt;/blockquote&amp;gt;</description>
            <link>http://www.old-computers.com/museum/adverts/sanyo_mbc550_advert_porte-ouverte.jpg</link>
        </advert>
        <advert>
            <description>&amp;lt;br&amp;gt;&amp;lt;font color=&amp;quot;red&amp;quot;&amp;gt;&amp;lt;strong&amp;gt;&amp;gt;&amp;nbsp;U.K. AD. (AUG. 86)&amp;lt;/strong&amp;gt;&amp;lt;/font&amp;gt;&amp;lt;br&amp;gt;&amp;lt;blockquote&amp;gt;U.K. prices:&amp;lt;br&amp;gt; Monochrome: &amp;lt;b&amp;gt;&amp;pound;299&amp;lt;/b&amp;gt;&amp;lt;br&amp;gt; Colour: &amp;lt;b&amp;gt;&amp;pound;399&amp;lt;/b&amp;gt;&amp;lt;/blockquote&amp;gt;</description>
            <link>http://www.old-computers.com/museum/adverts/Amstrad_6128_Advert_1.jpg</link>
        </advert>
        <advert>
            <description>&amp;lt;br&amp;gt;&amp;lt;font color=&amp;quot;red&amp;quot;&amp;gt;&amp;lt;strong&amp;gt;&amp;gt;&amp;nbsp;QL CATALOGUE #1&amp;lt;/strong&amp;gt;&amp;lt;/font&amp;gt;&amp;lt;br&amp;gt;&amp;lt;blockquote&amp;gt;Thanks to &amp;lt;a href=&amp;quot;http://blogs.linux.ie/fuzzbucket/archives/p/7/more/1/c/1/Vintage-Sinclair-QL-catalogue&amp;quot; target=&amp;quot;_blank&amp;quot;&amp;gt;fuzzbucket&amp;lt;/a&amp;gt; for this complete QL catalogue.&amp;lt;/blockquote&amp;gt;</description>
            <link>http://www.old-computers.com/museum/adverts/Sinclair_QL_Brochure1_s1.jpg</link>
        </advert>
        <advert>
            <description>&amp;lt;br&amp;gt;&amp;lt;font color=&amp;quot;red&amp;quot;&amp;gt;&amp;lt;strong&amp;gt;&amp;gt;&amp;nbsp;JAPANESE ADVERT&amp;lt;/strong&amp;gt;&amp;lt;/font&amp;gt;&amp;lt;br&amp;gt;&amp;lt;blockquote&amp;gt;&amp;lt;p class=&amp;quot;petitgris&amp;quot;&amp;gt;Thanks to &amp;lt;a href=&amp;quot;http://web.kyoto-inet.or.jp/people/s-oga/&amp;quot;&amp;gt;Soichiro Oga&amp;lt;/a&amp;gt; for this picture !&amp;lt;/p&amp;gt;&amp;lt;/blockquote&amp;gt;</description>
            <link>http://www.old-computers.com/museum/adverts/mitsubishi_multi16_advert1_s.gif</link>
        </advert>
        <advert>
            <description>&amp;lt;br&amp;gt;&amp;lt;font color=&amp;quot;red&amp;quot;&amp;gt;&amp;lt;strong&amp;gt;&amp;gt;&amp;nbsp;ADVERT&amp;lt;/strong&amp;gt;&amp;lt;/font&amp;gt;&amp;lt;br&amp;gt;&amp;lt;blockquote&amp;gt;&amp;lt;p class=&amp;quot;petitgris&amp;quot;&amp;gt;Thanks to Rui Santos for this picture&amp;lt;/p&amp;gt;&amp;lt;/blockquote&amp;gt;</description>
            <link>http://www.old-computers.com/museum/adverts/casio_fp1000_ad_0.jpg</link>
        </advert>
        <advert>
            <description>&amp;lt;br&amp;gt;&amp;lt;font color=&amp;quot;red&amp;quot;&amp;gt;&amp;lt;strong&amp;gt;&amp;gt;&amp;nbsp;FRENCH ADVERT (JAN. 1985)&amp;lt;/strong&amp;gt;&amp;lt;/font&amp;gt;&amp;lt;br&amp;gt;&amp;lt;blockquote&amp;gt;&amp;quot;After the compliments made to the Amstrad CPC-464, what could be added ?&amp;quot;&amp;lt;/blockquote&amp;gt;</description>
            <link>http://www.old-computers.com/museum/adverts/amstrad_cpc464_pub_tous-les-compliments.jpg</link>
        </advert>
        <advert>
            <description>&amp;lt;br&amp;gt;&amp;lt;font color=&amp;quot;red&amp;quot;&amp;gt;&amp;lt;strong&amp;gt;&amp;gt;&amp;nbsp;PROMOTIONAL LEAFLET&amp;lt;/strong&amp;gt;&amp;lt;/font&amp;gt;&amp;lt;br&amp;gt;&amp;lt;blockquote&amp;gt;&amp;lt;p class=&amp;quot;petitgris&amp;quot;&amp;gt;Thanks to Juan Antonio Maestre for this picture&amp;lt;/p&amp;gt;&amp;lt;/blockquote&amp;gt;</description>
            <link>http://www.old-computers.com/museum/adverts/trQ_h21_ss_catalog.jpg</link>
        </advert>
        <advert>
            <description>&amp;lt;br&amp;gt;&amp;lt;font color=&amp;quot;red&amp;quot;&amp;gt;&amp;lt;strong&amp;gt;&amp;gt;&amp;nbsp;ADVERT #2&amp;lt;/strong&amp;gt;&amp;lt;/font&amp;gt;&amp;lt;br&amp;gt;&amp;lt;blockquote&amp;gt;Yes, it's really him &amp;ndash; William Shatner (Captain Kirk).&amp;lt;br&amp;gt; Did they really use VIC-20 in the Enterprise?&amp;lt;br&amp;gt; That would certainly explain a lot of things...&amp;lt;p class=&amp;quot;petitgris&amp;quot;&amp;gt;Picture courtesy of &amp;lt;a href=&amp;quot;http://www.sbrowning.com/vintage&amp;quot;&amp;gt;Steve Browning, www.sbrowning.com/vintage&amp;lt;/a&amp;gt;.&amp;lt;/p&amp;gt;&amp;lt;/blockquote&amp;gt;</description>
            <link>http://www.old-computers.com/museum/adverts/commodore_vic20_ad_2.jpg</link>
        </advert>
        <advert>
            <description>&amp;lt;br&amp;gt;&amp;lt;font color=&amp;quot;red&amp;quot;&amp;gt;&amp;lt;strong&amp;gt;&amp;gt;&amp;nbsp;U.S. ADVERT (1976)&amp;lt;/strong&amp;gt;&amp;lt;/font&amp;gt;&amp;lt;br&amp;gt;&amp;lt;blockquote&amp;gt;&amp;lt;/blockquote&amp;gt;</description>
            <link>http://www.old-computers.com/museum/adverts/Polymorphic_Poly88_Advert_1.jpg</link>
        </advert>
        <advert>
            <description>&amp;lt;br&amp;gt;&amp;lt;font color=&amp;quot;red&amp;quot;&amp;gt;&amp;lt;strong&amp;gt;&amp;gt;&amp;nbsp;MAGAZINE COVER&amp;lt;/strong&amp;gt;&amp;lt;/font&amp;gt;&amp;lt;br&amp;gt;&amp;lt;blockquote&amp;gt;The Gridcase made the cover of SVM (french magazine) in january 1985&amp;lt;/blockquote&amp;gt;</description>
            <link>http://www.old-computers.com/museum/adverts/grid_gridcase_svm.jpg</link>
        </advert>
        <advert>
            <description>&amp;lt;br&amp;gt;&amp;lt;font color=&amp;quot;red&amp;quot;&amp;gt;&amp;lt;strong&amp;gt;&amp;gt;&amp;nbsp;FRENCH ADVERT (DEC. 1985)&amp;lt;/strong&amp;gt;&amp;lt;/font&amp;gt;&amp;lt;br&amp;gt;&amp;lt;blockquote&amp;gt;&amp;quot;MO5. Adventure built-in&amp;quot;&amp;lt;br&amp;gt; &amp;quot;All the world in a present&amp;quot;&amp;lt;/blockquote&amp;gt;</description>
            <link>http://www.old-computers.com/museum/adverts/thomson_mo5_advert_aventure-comprise.jpg</link>
        </advert>
        <advert>
            <description>&amp;lt;br&amp;gt;&amp;lt;font color=&amp;quot;red&amp;quot;&amp;gt;&amp;lt;strong&amp;gt;&amp;gt;&amp;nbsp;GERMAN AD #1&amp;lt;/strong&amp;gt;&amp;lt;/font&amp;gt;&amp;lt;br&amp;gt;&amp;lt;blockquote&amp;gt;&amp;quot;Welcome in the world of the &amp;quot;clean&amp;quot;-computers&amp;quot;&amp;lt;p class=&amp;quot;petitgris&amp;quot;&amp;gt;Courtesy of &amp;lt;b&amp;gt;www.sharpmz.org&amp;lt;/b&amp;gt;&amp;lt;/p&amp;gt;&amp;lt;/blockquote&amp;gt;</description>
            <link>http://www.old-computers.com/museum/adverts/Sharp_MZ700_Advert_1.jpg</link>
        </advert>
        <advert>
            <description>&amp;lt;br&amp;gt;&amp;lt;font color=&amp;quot;red&amp;quot;&amp;gt;&amp;lt;strong&amp;gt;&amp;gt;&amp;nbsp;PRINTERS ADVERT&amp;lt;/strong&amp;gt;&amp;lt;/font&amp;gt;&amp;lt;br&amp;gt;&amp;lt;blockquote&amp;gt;&amp;lt;/blockquote&amp;gt;</description>
            <link>http://www.old-computers.com/museum/adverts/Tandy_Color1_PrinterAdv_1.jpg</link>
        </advert>
        <advert>
            <description>&amp;lt;br&amp;gt;&amp;lt;font color=&amp;quot;red&amp;quot;&amp;gt;&amp;lt;strong&amp;gt;&amp;gt;&amp;nbsp;ADVERT #1&amp;lt;/strong&amp;gt;&amp;lt;/font&amp;gt;&amp;lt;br&amp;gt;&amp;lt;blockquote&amp;gt;The display says: &amp;quot;Personal computer Pravetz 82&amp;quot;&amp;lt;p class=&amp;quot;petitgris&amp;quot;&amp;gt;Thanks to &amp;lt;b&amp;gt;Bojidar Stefanov&amp;lt;/b&amp;gt;&amp;lt;/p&amp;gt;&amp;lt;/blockquote&amp;gt;</description>
            <link>http://www.old-computers.com/museum/adverts/Pravetz_Imko_Advert_s1.jpg</link>
        </advert>
    </adverts>
    <batteries></batteries>
    <builtInGames>Unknown</builtInGames>
    <buttons></buttons>
    <colors>Unknown</colors>
    <controllers></controllers>
    <coprocessor></coprocessor>
    <cpu>Unknown</cpu>
    <description>
Very little is known about this obscure Argentinian console! Though it uses a very similar Atari 2600 Jr case, This console if just a cheap copy of the Nintendo Famicom / NES.

In Argentina, several clone systems like can be found. A few can still be bought with cartridges for around 40 or 50 u$s.
 


</description>
    <emulators/>
    <graphics>Unknown</graphics>
    <gun></gun>
    <hardwares/>
    <image>http://www.old-computers.com/museum/photos/activision_family-game_1s.jpg</image>
    <keyboard></keyboard>
    <language>Unknown</language>
    <links/>
    <manufacturer>Industria Argentina</manufacturer>
    <media>Cartridges</media>
    <name>Activision Family Game</name>
    <numGames></numGames>
    <origin>Argentina</origin>
    <peripherals></peripherals>
    <ports>Two controller connectors, cartidge slot, power in, video output, expansion connector</ports>
    <power>External power supply</power>
    <price>Unknown</price>
    <production></production>
    <ram>Unknown</ram>
    <rom></rom>
    <screenshots>
        <shot>
            <description>&amp;lt;br&amp;gt;&amp;lt;font color=&amp;quot;red&amp;quot;&amp;gt;&amp;lt;strong&amp;gt;&amp;gt;&amp;nbsp;ACTIVISION FAMILY GAME&amp;lt;/strong&amp;gt;&amp;lt;/font&amp;gt;&amp;lt;br&amp;gt;&amp;lt;blockquote&amp;gt;&amp;lt;p class=&amp;quot;petitgris&amp;quot;&amp;gt;Thanks to &amp;lt;a href=&amp;quot;http://compuclasico.homelinux.net&amp;quot; target=&amp;quot;_blank&amp;quot;&amp;gt;Ricardo Saucedo&amp;lt;/a&amp;gt; for this picture.&amp;lt;/p&amp;gt;&amp;lt;/blockquote&amp;gt;</description>
            <link>http://www.old-computers.com/museum/photos/activision_family-game_1.jpg</link>
        </shot>
        <shot>
            <description>&amp;lt;br&amp;gt;&amp;lt;font color=&amp;quot;red&amp;quot;&amp;gt;&amp;lt;strong&amp;gt;&amp;gt;&amp;nbsp;BOTTOM&amp;lt;/strong&amp;gt;&amp;lt;/font&amp;gt;&amp;lt;br&amp;gt;&amp;lt;blockquote&amp;gt;&amp;lt;p class=&amp;quot;petitgris&amp;quot;&amp;gt;Thanks to &amp;lt;a href=&amp;quot;http://compuclasico.homelinux.net&amp;quot; target=&amp;quot;_blank&amp;quot;&amp;gt;Ricardo Saucedo&amp;lt;/a&amp;gt; for this picture.&amp;lt;/p&amp;gt;&amp;lt;/blockquote&amp;gt;</description>
            <link>http://www.old-computers.com/museum/photos/activision_family-game_below.jpg</link>
        </shot>
        <shot>
            <description>&amp;lt;br&amp;gt;&amp;lt;font color=&amp;quot;red&amp;quot;&amp;gt;&amp;lt;strong&amp;gt;&amp;gt;&amp;nbsp;REAR&amp;lt;/strong&amp;gt;&amp;lt;/font&amp;gt;&amp;lt;br&amp;gt;&amp;lt;blockquote&amp;gt;&amp;lt;p class=&amp;quot;petitgris&amp;quot;&amp;gt;Thanks to &amp;lt;a href=&amp;quot;http://compuclasico.homelinux.net&amp;quot; target=&amp;quot;_blank&amp;quot;&amp;gt;Ricardo Saucedo&amp;lt;/a&amp;gt; for this picture.&amp;lt;/p&amp;gt;&amp;lt;/blockquote&amp;gt;</description>
            <link>http://www.old-computers.com/museum/photos/activision_family-game_rear.jpg</link>
        </shot>
        <shot>
            <description>&amp;lt;br&amp;gt;&amp;lt;font color=&amp;quot;red&amp;quot;&amp;gt;&amp;lt;strong&amp;gt;&amp;gt;&amp;nbsp;DETAIL&amp;lt;/strong&amp;gt;&amp;lt;/font&amp;gt;&amp;lt;br&amp;gt;&amp;lt;blockquote&amp;gt;&amp;lt;p class=&amp;quot;petitgris&amp;quot;&amp;gt;Thanks to &amp;lt;a href=&amp;quot;http://compuclasico.homelinux.net&amp;quot; target=&amp;quot;_blank&amp;quot;&amp;gt;Ricardo Saucedo&amp;lt;/a&amp;gt; for this picture.&amp;lt;/p&amp;gt;&amp;lt;/blockquote&amp;gt;</description>
            <link>http://www.old-computers.com/museum/photos/activision_family-game_detail.jpg</link>
        </shot>
        <shot>
            <description>&amp;lt;br&amp;gt;&amp;lt;font color=&amp;quot;red&amp;quot;&amp;gt;&amp;lt;strong&amp;gt;&amp;gt;&amp;nbsp;OPENED&amp;lt;/strong&amp;gt;&amp;lt;/font&amp;gt;&amp;lt;br&amp;gt;&amp;lt;blockquote&amp;gt;&amp;lt;p class=&amp;quot;petitgris&amp;quot;&amp;gt;Thanks to &amp;lt;a href=&amp;quot;http://compuclasico.homelinux.net&amp;quot; target=&amp;quot;_blank&amp;quot;&amp;gt;Ricardo Saucedo&amp;lt;/a&amp;gt; for this picture.&amp;lt;/p&amp;gt;&amp;lt;/blockquote&amp;gt;</description>
            <link>http://www.old-computers.com/museum/photos/activision_family-game_opened.jpg</link>
        </shot>
        <shot>
            <description>&amp;lt;br&amp;gt;&amp;lt;font color=&amp;quot;red&amp;quot;&amp;gt;&amp;lt;strong&amp;gt;&amp;gt;&amp;nbsp;CHIPSETS&amp;lt;/strong&amp;gt;&amp;lt;/font&amp;gt;&amp;lt;br&amp;gt;&amp;lt;blockquote&amp;gt;&amp;lt;p class=&amp;quot;petitgris&amp;quot;&amp;gt;Thanks to &amp;lt;a href=&amp;quot;http://compuclasico.homelinux.net&amp;quot; target=&amp;quot;_blank&amp;quot;&amp;gt;Ricardo Saucedo&amp;lt;/a&amp;gt; for this picture.&amp;lt;/p&amp;gt;&amp;lt;/blockquote&amp;gt;</description>
            <link>http://www.old-computers.com/museum/photos/activision_family-game_chips.jpg</link>
        </shot>
    </screenshots>
    <size>Unknown</size>
    <sound></sound>
    <speed></speed>
    <switches></switches>
    <text></text>
    <type></type>
    <vram></vram>
    <year>Unknown</year>
</computer>
